{
  "xpaq3t4VhhmiF0t": [
    "MelonCmd_Bot_8209"
  ],
  "I0/L5IEUtwTAzhn": [
    "mbot"
  ],
  "d8F9aNn4OHTupW1": [
    "24aRecordV29236"
  ],
  "KDy2Y6tg6L1ig0p": [
    "Lookup"
  ],
  "p8Dxw5Xu7aJeyve": [
    "awa_ya"
  ],
  "9OcFnLOea0BqXFW": [
    "AfK_Bot"
  ],
  "Xr3wSAOVnudasgL": [
    "ICB_9"
  ],
  "HZd2QbnUMnHXocf": [
    "MelonCmd"
  ],
  "nie3ZNIEfJAwbBz": [
    "bulubulu"
  ],
  "ZV/1CU0Yu7vmOU4": [
    "Zxc_Jy_qwq"
  ],
  "obazugNiR99XjT6": [
    "sora1"
  ],
  "xqpEvMdcsN89SjB": [
    "alepha"
  ],
  "Lc18G6PLtvZ3Jxv": [
    "Br_O_Ken",
    "game_ya"
  ],
  "yV5+QfwMVgBmiJd": [
    "D"
  ],
  "7XRzoTdmvXaaPgB": [
    "Immortal_",
    "Immortal__"
  ],
  "DQtB/URsIsYGSs8": [
    "4n0n4me__"
  ]
}